{
	"configurations" : 
	[
		{
			"directories" : 
			[
				{
					"build" : ".",
					"childIndexes" : 
					[
						1,
						2,
						3,
						4,
						5,
						6
					],
					"jsonFile" : "directory-.-Debug-f5ebdc15457944623624.json",
					"minimumCMakeVersion" : 
					{
						"string" : "3.23"
					},
					"projectIndex" : 0,
					"source" : "."
				},
				{
					"build" : "0-intro",
					"jsonFile" : "directory-0-intro-Debug-13b31864666c85ec368a.json",
					"minimumCMakeVersion" : 
					{
						"string" : "3.23"
					},
					"parentIndex" : 0,
					"projectIndex" : 0,
					"source" : "0-intro",
					"targetIndexes" : 
					[
						10,
						12
					]
				},
				{
					"build" : "1-types-io",
					"jsonFile" : "directory-1-types-io-Debug-557521dfdc9490a16800.json",
					"minimumCMakeVersion" : 
					{
						"string" : "3.23"
					},
					"parentIndex" : 0,
					"projectIndex" : 0,
					"source" : "1-types-io",
					"targetIndexes" : 
					[
						0,
						1,
						5,
						24,
						31
					]
				},
				{
					"build" : "2-if-for-array",
					"jsonFile" : "directory-2-if-for-array-Debug-918b279c183e85f93c38.json",
					"minimumCMakeVersion" : 
					{
						"string" : "3.23"
					},
					"parentIndex" : 0,
					"projectIndex" : 0,
					"source" : "2-if-for-array",
					"targetIndexes" : 
					[
						13,
						14,
						15,
						17,
						20,
						21,
						22,
						23
					]
				},
				{
					"build" : "3-for-a-while",
					"jsonFile" : "directory-3-for-a-while-Debug-6725d83b46090e7dcb65.json",
					"minimumCMakeVersion" : 
					{
						"string" : "3.23"
					},
					"parentIndex" : 0,
					"projectIndex" : 0,
					"source" : "3-for-a-while",
					"targetIndexes" : 
					[
						2,
						6,
						25,
						27,
						29,
						32
					]
				},
				{
					"build" : "4-loops",
					"jsonFile" : "directory-4-loops-Debug-a011b47ac677f7330f84.json",
					"minimumCMakeVersion" : 
					{
						"string" : "3.23"
					},
					"parentIndex" : 0,
					"projectIndex" : 0,
					"source" : "4-loops",
					"targetIndexes" : 
					[
						4,
						7,
						18
					]
				},
				{
					"build" : "5-function",
					"jsonFile" : "directory-5-function-Debug-0e5d873ea684b0dac154.json",
					"minimumCMakeVersion" : 
					{
						"string" : "3.23"
					},
					"parentIndex" : 0,
					"projectIndex" : 0,
					"source" : "5-function",
					"targetIndexes" : 
					[
						3,
						8,
						9,
						11,
						16,
						19,
						26,
						28,
						30,
						33
					]
				}
			],
			"name" : "Debug",
			"projects" : 
			[
				{
					"directoryIndexes" : 
					[
						0,
						1,
						2,
						3,
						4,
						5,
						6
					],
					"name" : "2022_cpl_coding_1",
					"targetIndexes" : 
					[
						0,
						1,
						2,
						3,
						4,
						5,
						6,
						7,
						8,
						9,
						10,
						11,
						12,
						13,
						14,
						15,
						16,
						17,
						18,
						19,
						20,
						21,
						22,
						23,
						24,
						25,
						26,
						27,
						28,
						29,
						30,
						31,
						32,
						33
					]
				}
			],
			"targets" : 
			[
				{
					"directoryIndex" : 2,
					"id" : "admin::@592ee50047900f3dac72",
					"jsonFile" : "target-admin-Debug-7ce92910df4cdacb7d58.json",
					"name" : "admin",
					"projectIndex" : 0
				},
				{
					"directoryIndex" : 2,
					"id" : "admin-scanf::@592ee50047900f3dac72",
					"jsonFile" : "target-admin-scanf-Debug-1ddbac819092b012a601.json",
					"name" : "admin-scanf",
					"projectIndex" : 0
				},
				{
					"directoryIndex" : 4,
					"id" : "binary-search::@a95ac0ded7e648dc8f12",
					"jsonFile" : "target-binary-search-Debug-d8eb52c7972cf0c96be6.json",
					"name" : "binary-search",
					"projectIndex" : 0
				},
				{
					"directoryIndex" : 6,
					"id" : "binary-search-func::@18b7eb9d20db78c69f22",
					"jsonFile" : "target-binary-search-func-Debug-40aacfda07bf64e2f4f3.json",
					"name" : "binary-search-func",
					"projectIndex" : 0
				},
				{
					"directoryIndex" : 5,
					"id" : "bubble-sort::@b89cdeb732e8a284e7d7",
					"jsonFile" : "target-bubble-sort-Debug-435633cba175af5c4cdd.json",
					"name" : "bubble-sort",
					"projectIndex" : 0
				},
				{
					"directoryIndex" : 2,
					"id" : "circle::@592ee50047900f3dac72",
					"jsonFile" : "target-circle-Debug-3973f49086368ecefad9.json",
					"name" : "circle",
					"projectIndex" : 0
				},
				{
					"directoryIndex" : 4,
					"id" : "digits::@a95ac0ded7e648dc8f12",
					"jsonFile" : "target-digits-Debug-26722f9d0e42842e79ad.json",
					"name" : "digits",
					"projectIndex" : 0
				},
				{
					"directoryIndex" : 5,
					"id" : "game-of-life::@b89cdeb732e8a284e7d7",
					"jsonFile" : "target-game-of-life-Debug-80fa78ab50037ac39d12.json",
					"name" : "game-of-life",
					"projectIndex" : 0
				},
				{
					"directoryIndex" : 6,
					"id" : "game-of-life-func::@18b7eb9d20db78c69f22",
					"jsonFile" : "target-game-of-life-func-Debug-e938c5d0957108983451.json",
					"name" : "game-of-life-func",
					"projectIndex" : 0
				},
				{
					"directoryIndex" : 6,
					"id" : "game-of-life-transformed-func::@18b7eb9d20db78c69f22",
					"jsonFile" : "target-game-of-life-transformed-func-Debug-5eb8c430cf95c651625c.json",
					"name" : "game-of-life-transformed-func",
					"projectIndex" : 0
				},
				{
					"directoryIndex" : 1,
					"id" : "guess::@53414a9831fb1dd599fc",
					"jsonFile" : "target-guess-Debug-0905334cf869ef42b152.json",
					"name" : "guess",
					"projectIndex" : 0
				},
				{
					"directoryIndex" : 6,
					"id" : "guess-func::@18b7eb9d20db78c69f22",
					"jsonFile" : "target-guess-func-Debug-5493ac8258aa651dcb86.json",
					"name" : "guess-func",
					"projectIndex" : 0
				},
				{
					"directoryIndex" : 1,
					"id" : "hello::@53414a9831fb1dd599fc",
					"jsonFile" : "target-hello-Debug-27a08a829266e65bf406.json",
					"name" : "hello",
					"projectIndex" : 0
				},
				{
					"directoryIndex" : 3,
					"id" : "leap::@1877d974addea39212c3",
					"jsonFile" : "target-leap-Debug-156429768e3300c9b437.json",
					"name" : "leap",
					"projectIndex" : 0
				},
				{
					"directoryIndex" : 3,
					"id" : "leap-else-if::@1877d974addea39212c3",
					"jsonFile" : "target-leap-else-if-Debug-471b3851682878cab093.json",
					"name" : "leap-else-if",
					"projectIndex" : 0
				},
				{
					"directoryIndex" : 3,
					"id" : "leap-elseif::@1877d974addea39212c3",
					"jsonFile" : "target-leap-elseif-Debug-ae469945971b64530ff2.json",
					"name" : "leap-elseif",
					"projectIndex" : 0
				},
				{
					"directoryIndex" : 6,
					"id" : "leap-func::@18b7eb9d20db78c69f22",
					"jsonFile" : "target-leap-func-Debug-add4f8ced8699c714600.json",
					"name" : "leap-func",
					"projectIndex" : 0
				},
				{
					"directoryIndex" : 3,
					"id" : "leap-if-else::@1877d974addea39212c3",
					"jsonFile" : "target-leap-if-else-Debug-5a0c2541d6f4be689388.json",
					"name" : "leap-if-else",
					"projectIndex" : 0
				},
				{
					"directoryIndex" : 5,
					"id" : "merge::@b89cdeb732e8a284e7d7",
					"jsonFile" : "target-merge-Debug-5435dc2b47e440524fd0.json",
					"name" : "merge",
					"projectIndex" : 0
				},
				{
					"directoryIndex" : 6,
					"id" : "merge-func::@18b7eb9d20db78c69f22",
					"jsonFile" : "target-merge-func-Debug-6e1f0c5c5d55d246bdb8.json",
					"name" : "merge-func",
					"projectIndex" : 0
				},
				{
					"directoryIndex" : 3,
					"id" : "min-array::@1877d974addea39212c3",
					"jsonFile" : "target-min-array-Debug-71b88e0634c6c2b28ef5.json",
					"name" : "min-array",
					"projectIndex" : 0
				},
				{
					"directoryIndex" : 3,
					"id" : "min-array-input::@1877d974addea39212c3",
					"jsonFile" : "target-min-array-input-Debug-dcfcce13b52362ce2606.json",
					"name" : "min-array-input",
					"projectIndex" : 0
				},
				{
					"directoryIndex" : 3,
					"id" : "min-of-three::@1877d974addea39212c3",
					"jsonFile" : "target-min-of-three-Debug-99c0a686561375bc1ee1.json",
					"name" : "min-of-three",
					"projectIndex" : 0
				},
				{
					"directoryIndex" : 3,
					"id" : "min-of-two::@1877d974addea39212c3",
					"jsonFile" : "target-min-of-two-Debug-a1eb9a0c0181d011d760.json",
					"name" : "min-of-two",
					"projectIndex" : 0
				},
				{
					"directoryIndex" : 2,
					"id" : "mol::@592ee50047900f3dac72",
					"jsonFile" : "target-mol-Debug-b10cbb5af95e3a6fd496.json",
					"name" : "mol",
					"projectIndex" : 0
				},
				{
					"directoryIndex" : 4,
					"id" : "palindrome::@a95ac0ded7e648dc8f12",
					"jsonFile" : "target-palindrome-Debug-ffb34b19bb4e9bcab135.json",
					"name" : "palindrome",
					"projectIndex" : 0
				},
				{
					"directoryIndex" : 6,
					"id" : "palindrome-func::@18b7eb9d20db78c69f22",
					"jsonFile" : "target-palindrome-func-Debug-b948329e4f92dc8096ee.json",
					"name" : "palindrome-func",
					"projectIndex" : 0
				},
				{
					"directoryIndex" : 4,
					"id" : "primes::@a95ac0ded7e648dc8f12",
					"jsonFile" : "target-primes-Debug-d264b3f338deb486c937.json",
					"name" : "primes",
					"projectIndex" : 0
				},
				{
					"directoryIndex" : 6,
					"id" : "primes-func::@18b7eb9d20db78c69f22",
					"jsonFile" : "target-primes-func-Debug-b038cc8277e44c0cd2ee.json",
					"name" : "primes-func",
					"projectIndex" : 0
				},
				{
					"directoryIndex" : 4,
					"id" : "selection-sort::@a95ac0ded7e648dc8f12",
					"jsonFile" : "target-selection-sort-Debug-57717c7f491aec3d7087.json",
					"name" : "selection-sort",
					"projectIndex" : 0
				},
				{
					"directoryIndex" : 6,
					"id" : "selection-sort-func::@18b7eb9d20db78c69f22",
					"jsonFile" : "target-selection-sort-func-Debug-da8d4000775c18d81cc3.json",
					"name" : "selection-sort-func",
					"projectIndex" : 0
				},
				{
					"directoryIndex" : 2,
					"id" : "sphere::@592ee50047900f3dac72",
					"jsonFile" : "target-sphere-Debug-637ddbd7a5f42bf49cbc.json",
					"name" : "sphere",
					"projectIndex" : 0
				},
				{
					"directoryIndex" : 4,
					"id" : "stars::@a95ac0ded7e648dc8f12",
					"jsonFile" : "target-stars-Debug-7b16750c42da243eb1c6.json",
					"name" : "stars",
					"projectIndex" : 0
				},
				{
					"directoryIndex" : 6,
					"id" : "stars-func::@18b7eb9d20db78c69f22",
					"jsonFile" : "target-stars-func-Debug-579d8bdb676982d4722d.json",
					"name" : "stars-func",
					"projectIndex" : 0
				}
			]
		}
	],
	"kind" : "codemodel",
	"paths" : 
	{
		"build" : "/home/hengxin/Documents/cpl/2022-cpl-coding-1/cmake-build-debug",
		"source" : "/home/hengxin/Documents/cpl/2022-cpl-coding-1"
	},
	"version" : 
	{
		"major" : 2,
		"minor" : 4
	}
}
